jupyai/__init__.py
jupyai/_version.py
jupyai/autocomplete.py
jupyai/exceptions.py
jupyai/handlers.py
jupyai/tests/__init__.py
jupyai/tests/test_autocomplete.py
jupyai/tests/test_handlers.py
jupyai-0.1.2.data/data/etc/jupyter/jupyter_server_config.d/jupyai.json
jupyai-0.1.2.data/data/share/jupyter/labextensions/jupyai/package.json
jupyai-0.1.2.data/data/share/jupyter/labextensions/jupyai/schemas/jupyai/package.json.orig
jupyai-0.1.2.data/data/share/jupyter/labextensions/jupyai/schemas/jupyai/plugin.json
jupyai-0.1.2.data/data/share/jupyter/labextensions/jupyai/static/747.660103916f6453ffc8c2.js
jupyai-0.1.2.data/data/share/jupyter/labextensions/jupyai/static/763.1f28c07d3cf2f9be579a.js
jupyai-0.1.2.data/data/share/jupyter/labextensions/jupyai/static/remoteEntry.898e22d415840ce6bb57.js
jupyai-0.1.2.data/data/share/jupyter/labextensions/jupyai/static/style.js
jupyai-0.1.2.data/data/share/jupyter/labextensions/jupyai/static/third-party-licenses.json
jupyai-0.1.2.data/data/share/jupyter/labextensions/jupyai/install.json
jupyai-0.1.2.dist-info/METADATA
jupyai-0.1.2.dist-info/WHEEL
jupyai-0.1.2.dist-info/licenses/LICENSE
jupyai-0.1.2.dist-info/RECORD
